muax/__init__.py
muax/episode_tracer.py
muax/loss.py
muax/model.py
muax/nn.py
muax/replay_buffer.py
muax/test.py
muax/train.py
muax/utils.py
muax/wrappers.py
muax-0.0.2.8.3.dist-info/LICENSE
muax-0.0.2.8.3.dist-info/METADATA
muax-0.0.2.8.3.dist-info/WHEEL
muax-0.0.2.8.3.dist-info/top_level.txt
muax-0.0.2.8.3.dist-info/RECORD
